question_type_cls/__init__.py
question_type_cls/math_type_cls.py
question_type_cls/configs/__init__.py
question_type_cls/configs/key_type.py
question_type_cls/dataset/__init__.py
question_type_cls/dataset/accent_processor.py
question_type_cls/dataset/normalize_character.py
question_type_cls/dataset/preprocess.py
question_type_cls/inference/__init__.py
question_type_cls/inference/predict.py
question_type_cls/inference/rulebased.py
question_type_cls/utils/__init__.py
question_type_cls/utils/data_utils.py
question_type_cls/utils/model_utils.py
question_type_cls/utils/special_characters.py
MQTC-0.0.2.dist-info/METADATA
MQTC-0.0.2.dist-info/WHEEL
MQTC-0.0.2.dist-info/top_level.txt
MQTC-0.0.2.dist-info/RECORD
