Metadata-Version: 2.1
Name: MQTC
Version: 0.0.2
Summary: Question CLS Package
Author: mlt
Author-email: mlt@ftech.ai
Classifier: Programming Language :: Python :: 3
Classifier: License :: OSI Approved :: MIT License
Classifier: Operating System :: OS Independent
Requires-Python: >=3.6
